<?xml version='1.0' encoding='utf8'?>
<annotation>
	<folder>img</folder>
	<filename>rubbish-2667.jpg</filename>
	<path>D:\Allpackage\Label\img\rubbish-2667.jpg</path>
	<source>
		<database>Unknown</database>
	</source>
	<size>
		<width>1920</width>
		<height>1080</height>
		<depth>3</depth>
	</size>
	<segmented>0</segmented>
	<object>
		<name>floater</name>
		<pose>Unspecified</pose>
		<truncated>0</truncated>
		<difficult>0</difficult>
		<bndbox>
			<xmin>1177</xmin>
			<ymin>510</ymin>
			<xmax>1348</xmax>
			<ymax>660</ymax>
		</bndbox>
	</object>
	<object>
		<name>floater</name>
		<pose>Unspecified</pose>
		<truncated>0</truncated>
		<difficult>0</difficult>
		<bndbox>
			<xmin>1742</xmin>
			<ymin>642</ymin>
			<xmax>1915</xmax>
			<ymax>870</ymax>
		</bndbox>
	</object>
	<object>
		<name>floater</name>
		<pose>Unspecified</pose>
		<truncated>0</truncated>
		<difficult>0</difficult>
		<bndbox>
			<xmin>1522</xmin>
			<ymin>945</ymin>
			<xmax>1720</xmax>
			<ymax>1079</ymax>
		</bndbox>
	</object>
	<object>
		<name>floater</name>
		<pose>Unspecified</pose>
		<truncated>1</truncated>
		<difficult>0</difficult>
		<bndbox>
			<xmin>1029</xmin>
			<ymin>1002</ymin>
			<xmax>1221</xmax>
			<ymax>1080</ymax>
		</bndbox>
	</object>
	<object>
		<name>floater</name>
		<pose>Unspecified</pose>
		<truncated>0</truncated>
		<difficult>0</difficult>
		<bndbox>
			<xmin>775</xmin>
			<ymin>197</ymin>
			<xmax>919</xmax>
			<ymax>387</ymax>
		</bndbox>
	</object>
	<object>
		<name>floater</name>
		<pose>Unspecified</pose>
		<truncated>0</truncated>
		<difficult>0</difficult>
		<bndbox>
			<xmin>651</xmin>
			<ymin>259</ymin>
			<xmax>731</xmax>
			<ymax>347</ymax>
		</bndbox>
	</object>
	<object>
		<name>floater</name>
		<pose>Unspecified</pose>
		<truncated>0</truncated>
		<difficult>0</difficult>
		<bndbox>
			<xmin>619</xmin>
			<ymin>3</ymin>
			<xmax>1017</xmax>
			<ymax>174</ymax>
		</bndbox>
	</object>
</annotation>