<?xml version='1.0' encoding='utf8'?>
<annotation>
	<folder>img</folder>
	<filename>rubbish-2863.jpg</filename>
	<path>D:\Allpackage\Label\img\rubbish-2863.jpg</path>
	<source>
		<database>Unknown</database>
	</source>
	<size>
		<width>1920</width>
		<height>1080</height>
		<depth>3</depth>
	</size>
	<segmented>0</segmented>
	<object>
		<name>floater</name>
		<pose>Unspecified</pose>
		<truncated>0</truncated>
		<difficult>0</difficult>
		<bndbox>
			<xmin>1369</xmin>
			<ymin>11</ymin>
			<xmax>1629</xmax>
			<ymax>253</ymax>
		</bndbox>
	</object>
	<object>
		<name>floater</name>
		<pose>Unspecified</pose>
		<truncated>1</truncated>
		<difficult>0</difficult>
		<bndbox>
			<xmin>1610</xmin>
			<ymin>1</ymin>
			<xmax>1803</xmax>
			<ymax>230</ymax>
		</bndbox>
	</object>
	<object>
		<name>floater</name>
		<pose>Unspecified</pose>
		<truncated>1</truncated>
		<difficult>0</difficult>
		<bndbox>
			<xmin>1714</xmin>
			<ymin>400</ymin>
			<xmax>1920</xmax>
			<ymax>558</ymax>
		</bndbox>
	</object>
	<object>
		<name>floater</name>
		<pose>Unspecified</pose>
		<truncated>1</truncated>
		<difficult>0</difficult>
		<bndbox>
			<xmin>761</xmin>
			<ymin>497</ymin>
			<xmax>1433</xmax>
			<ymax>1080</ymax>
		</bndbox>
	</object>
	<object>
		<name>floater</name>
		<pose>Unspecified</pose>
		<truncated>0</truncated>
		<difficult>0</difficult>
		<bndbox>
			<xmin>1427</xmin>
			<ymin>824</ymin>
			<xmax>1674</xmax>
			<ymax>1032</ymax>
		</bndbox>
	</object>
</annotation>