<?xml version='1.0' encoding='utf8'?>
<annotation>
	<folder>img</folder>
	<filename>rubbish-2919.jpg</filename>
	<path>D:\Research\labelimg\lx\img\rubbish-2919.jpg</path>
	<source>
		<database>Unknown</database>
	</source>
	<size>
		<width>1920</width>
		<height>1080</height>
		<depth>3</depth>
	</size>
	<segmented>0</segmented>
	<object>
		<name>floater</name>
		<pose>Unspecified</pose>
		<truncated>0</truncated>
		<difficult>0</difficult>
		<bndbox>
			<xmin>1006</xmin>
			<ymin>449</ymin>
			<xmax>1208</xmax>
			<ymax>724</ymax>
		</bndbox>
	</object>
	<object>
		<name>floater</name>
		<pose>Unspecified</pose>
		<truncated>0</truncated>
		<difficult>0</difficult>
		<bndbox>
			<xmin>863</xmin>
			<ymin>611</ymin>
			<xmax>1369</xmax>
			<ymax>999</ymax>
		</bndbox>
	</object>
	<object>
		<name>floater</name>
		<pose>Unspecified</pose>
		<truncated>0</truncated>
		<difficult>0</difficult>
		<bndbox>
			<xmin>2</xmin>
			<ymin>598</ymin>
			<xmax>114</xmax>
			<ymax>808</ymax>
		</bndbox>
	</object>
	<object>
		<name>floater</name>
		<pose>Unspecified</pose>
		<truncated>1</truncated>
		<difficult>0</difficult>
		<bndbox>
			<xmin>6</xmin>
			<ymin>1016</ymin>
			<xmax>242</xmax>
			<ymax>1080</ymax>
		</bndbox>
	</object>
</annotation>