<?xml version='1.0' encoding='utf8'?>
<annotation>
	<folder>img</folder>
	<filename>rubbish-4155.jpg</filename>
	<path>D:\detect_model_dir\yolo_mix_dataset\yolov5\paper_data\mmm\img\rubbish-4155.jpg</path>
	<source>
		<database>Unknown</database>
	</source>
	<size>
		<width>1920</width>
		<height>1080</height>
		<depth>3</depth>
	</size>
	<segmented>0</segmented>
	<object>
		<name>floater</name>
		<pose>Unspecified</pose>
		<truncated>0</truncated>
		<difficult>0</difficult>
		<bndbox>
			<xmin>795</xmin>
			<ymin>183</ymin>
			<xmax>919</xmax>
			<ymax>299</ymax>
		</bndbox>
	</object>
	<object>
		<name>floater</name>
		<pose>Unspecified</pose>
		<truncated>0</truncated>
		<difficult>0</difficult>
		<bndbox>
			<xmin>1360</xmin>
			<ymin>461</ymin>
			<xmax>1544</xmax>
			<ymax>625</ymax>
		</bndbox>
	</object>
	<object>
		<name>floater</name>
		<pose>Unspecified</pose>
		<truncated>0</truncated>
		<difficult>0</difficult>
		<bndbox>
			<xmin>1541</xmin>
			<ymin>442</ymin>
			<xmax>1708</xmax>
			<ymax>572</ymax>
		</bndbox>
	</object>
	<object>
		<name>floater</name>
		<pose>Unspecified</pose>
		<truncated>0</truncated>
		<difficult>0</difficult>
		<bndbox>
			<xmin>456</xmin>
			<ymin>32</ymin>
			<xmax>744</xmax>
			<ymax>251</ymax>
		</bndbox>
	</object>
	<object>
		<name>floater</name>
		<pose>Unspecified</pose>
		<truncated>0</truncated>
		<difficult>0</difficult>
		<bndbox>
			<xmin>400</xmin>
			<ymin>11</ymin>
			<xmax>563</xmax>
			<ymax>95</ymax>
		</bndbox>
	</object>
	<object>
		<name>floater</name>
		<pose>Unspecified</pose>
		<truncated>0</truncated>
		<difficult>0</difficult>
		<bndbox>
			<xmin>503</xmin>
			<ymin>34</ymin>
			<xmax>611</xmax>
			<ymax>127</ymax>
		</bndbox>
	</object>
	<object>
		<name>floater</name>
		<pose>Unspecified</pose>
		<truncated>1</truncated>
		<difficult>0</difficult>
		<bndbox>
			<xmin>661</xmin>
			<ymin>1</ymin>
			<xmax>839</xmax>
			<ymax>45</ymax>
		</bndbox>
	</object>
</annotation>