<?xml version='1.0' encoding='utf8'?>
<annotation>
	<folder>1000-1999</folder>
	<filename>fishing-1,645.jpg</filename>
	<path>G:\BaiduNetdiskDownload\rubbish\image\1000-1999\fishing-1,645.jpg</path>
	<source>
		<database>Unknown</database>
	</source>
	<size>
		<width>1920</width>
		<height>1080</height>
		<depth>3</depth>
	</size>
	<segmented>0</segmented>
	<object>
		<name>floater</name>
		<pose>Unspecified</pose>
		<truncated>1</truncated>
		<difficult>0</difficult>
		<bndbox>
			<xmin>1</xmin>
			<ymin>335</ymin>
			<xmax>60</xmax>
			<ymax>380</ymax>
		</bndbox>
	</object>
	<object>
		<name>floater</name>
		<pose>Unspecified</pose>
		<truncated>1</truncated>
		<difficult>0</difficult>
		<bndbox>
			<xmin>1</xmin>
			<ymin>360</ymin>
			<xmax>96</xmax>
			<ymax>435</ymax>
		</bndbox>
	</object>
	<object>
		<name>floater</name>
		<pose>Unspecified</pose>
		<truncated>0</truncated>
		<difficult>0</difficult>
		<bndbox>
			<xmin>96</xmin>
			<ymin>350</ymin>
			<xmax>191</xmax>
			<ymax>438</ymax>
		</bndbox>
	</object>
	<object>
		<name>floater</name>
		<pose>Unspecified</pose>
		<truncated>0</truncated>
		<difficult>0</difficult>
		<bndbox>
			<xmin>402</xmin>
			<ymin>431</ymin>
			<xmax>565</xmax>
			<ymax>514</ymax>
		</bndbox>
	</object>
	<object>
		<name>floater</name>
		<pose>Unspecified</pose>
		<truncated>0</truncated>
		<difficult>0</difficult>
		<bndbox>
			<xmin>529</xmin>
			<ymin>479</ymin>
			<xmax>583</xmax>
			<ymax>534</ymax>
		</bndbox>
	</object>
	<object>
		<name>floater</name>
		<pose>Unspecified</pose>
		<truncated>0</truncated>
		<difficult>0</difficult>
		<bndbox>
			<xmin>641</xmin>
			<ymin>480</ymin>
			<xmax>711</xmax>
			<ymax>594</ymax>
		</bndbox>
	</object>
	<object>
		<name>floater</name>
		<pose>Unspecified</pose>
		<truncated>0</truncated>
		<difficult>0</difficult>
		<bndbox>
			<xmin>644</xmin>
			<ymin>734</ymin>
			<xmax>721</xmax>
			<ymax>780</ymax>
		</bndbox>
	</object>
	<object>
		<name>floater</name>
		<pose>Unspecified</pose>
		<truncated>0</truncated>
		<difficult>0</difficult>
		<bndbox>
			<xmin>803</xmin>
			<ymin>640</ymin>
			<xmax>869</xmax>
			<ymax>821</ymax>
		</bndbox>
	</object>
	<object>
		<name>floater</name>
		<pose>Unspecified</pose>
		<truncated>0</truncated>
		<difficult>0</difficult>
		<bndbox>
			<xmin>853</xmin>
			<ymin>769</ymin>
			<xmax>898</xmax>
			<ymax>831</ymax>
		</bndbox>
	</object>
	<object>
		<name>floater</name>
		<pose>Unspecified</pose>
		<truncated>0</truncated>
		<difficult>0</difficult>
		<bndbox>
			<xmin>1121</xmin>
			<ymin>550</ymin>
			<xmax>1233</xmax>
			<ymax>606</ymax>
		</bndbox>
	</object>
	<object>
		<name>floater</name>
		<pose>Unspecified</pose>
		<truncated>0</truncated>
		<difficult>0</difficult>
		<bndbox>
			<xmin>1133</xmin>
			<ymin>514</ymin>
			<xmax>1248</xmax>
			<ymax>575</ymax>
		</bndbox>
	</object>
	<object>
		<name>floater</name>
		<pose>Unspecified</pose>
		<truncated>0</truncated>
		<difficult>0</difficult>
		<bndbox>
			<xmin>1041</xmin>
			<ymin>465</ymin>
			<xmax>1114</xmax>
			<ymax>518</ymax>
		</bndbox>
	</object>
</annotation>